MANIFEST.in
README.txt
setup.py
XStatic_Angular_nvd3.egg-info/PKG-INFO
XStatic_Angular_nvd3.egg-info/SOURCES.txt
XStatic_Angular_nvd3.egg-info/dependency_links.txt
XStatic_Angular_nvd3.egg-info/namespace_packages.txt
XStatic_Angular_nvd3.egg-info/not-zip-safe
XStatic_Angular_nvd3.egg-info/top_level.txt
xstatic/__init__.py
xstatic/pkg/__init__.py
xstatic/pkg/angular_nvd3/__init__.py
xstatic/pkg/angular_nvd3/data/angularjs-nvd3-directives.js