Metadata-Version: 1.0
Name: XStatic-Angular-nvd3
Version: 0.0.8.1
Summary: Angular-nvd3 0.0.8 (XStatic packaging standard)
Home-page: https://cmaurer.github.io/angularjs-nvd3-directives/
Author: Thai Tran
Author-email: tqtran@us.ibm.com
License: (same as Angular-nvd3)
Keywords: xstatic angular chart d3 nvd3 directives
Platform: any
